{"skeleton":{"hash":"f+LPMhfeAOhjO/L7WulSlthh8RA","spine":"3.6.38","width":900.78,"height":901.04,"images":"./images/"},"bones":[{"name":"root"},{"name":"shouji_tx4","parent":"root"},{"name":"shouji_tx4_1","parent":"shouji_tx4"},{"name":"bone","parent":"shouji_tx4_1","length":267.96,"x":-112.81,"y":-6.18},{"name":"shouji_tx4_2","parent":"shouji_tx4"},{"name":"bone2","parent":"shouji_tx4_2","length":267.96,"rotation":90},{"name":"shouji_tx4_3","parent":"shouji_tx4"},{"name":"bone3","parent":"shouji_tx4_3","length":267.96,"rotation":90},{"name":"hit","parent":"root"},{"name":"hit2","parent":"root"},{"name":"pojun_hit2","parent":"hit","x":-0.78,"y":-1.04},{"name":"pojun_hit3","parent":"hit"},{"name":"pojun_hit4","parent":"hit"},{"name":"pojun_hit5","parent":"hit"},{"name":"pojun_hit6","parent":"hit"},{"name":"pojun_hit7","parent":"hit"},{"name":"pojun_hit8","parent":"hit2","x":-0.78,"y":-1.04},{"name":"pojun_hit9","parent":"hit2"},{"name":"pojun_hit10","parent":"hit2"},{"name":"shouji_tx1","parent":"root"},{"name":"shouji_tx2","parent":"root"},{"name":"shouji_tx3","parent":"root","y":-7.57,"scaleX":0.929},{"name":"shouji_tx5","parent":"root"},{"name":"shouji_tx6","parent":"root"},{"name":"shouji_tx7","parent":"root"}],"slots":[{"name":"vfx/shouji/shouji_tx1","bone":"shouji_tx1","attachment":"vfx/shouji/shouji_tx1"},{"name":"vfx/shouji/shouji_tx2_00_bl_add","bone":"shouji_tx2","attachment":"vfx/shouji/shouji_tx2_16","blend":"additive"},{"name":"vfx/shouji/shouji_tx3_bl_add","bone":"shouji_tx3","attachment":"vfx/shouji/shouji_tx3","blend":"additive"},{"name":"hit/pojun_hit2_00","bone":"pojun_hit2","attachment":"hit/pojun_hit2_00"},{"name":"hit/pojun_hit2_0","bone":"pojun_hit8","attachment":"hit/pojun_hit2_00"},{"name":"hit/pojun_hit3_00","bone":"pojun_hit3","attachment":"hit/pojun_hit3_00"},{"name":"hit/pojun_hit3_0","bone":"pojun_hit9","attachment":"hit/pojun_hit3_00"},{"name":"hit/pojun_hit5_00","bone":"pojun_hit5","attachment":"hit/pojun_hit5_00"},{"name":"hit/pojun_hit6_00","bone":"pojun_hit6","attachment":"hit/pojun_hit6_00"},{"name":"vfx/shouji/shouji_tx4_bl_add","bone":"bone","attachment":"vfx/shouji/shouji_tx4","blend":"additive"},{"name":"vfx/shouji/shouji_tx5_bl_add","bone":"bone2","attachment":"vfx/shouji/shouji_tx4","blend":"additive"},{"name":"vfx/shouji/shouji_tx6_bl_add","bone":"bone3","attachment":"vfx/shouji/shouji_tx4","blend":"additive"},{"name":"hit/pojun_hit4_00_bl_add","bone":"pojun_hit4","blend":"additive"},{"name":"hit/pojun_hit4_0_bl_add","bone":"pojun_hit10","blend":"additive"},{"name":"hit/pojun_hit7_00","bone":"pojun_hit7","attachment":"hit/pojun_hit7_00"},{"name":"vfx/shouji/shouji_tx7_bl_add","bone":"shouji_tx5","attachment":"vfx/shouji/shouji_tx5","blend":"additive"},{"name":"vfx/shouji/shouji_tx8","bone":"shouji_tx6","attachment":"vfx/shouji/shouji_tx6"},{"name":"vfx/shouji/shouji_tx7_00_bl_add","bone":"shouji_tx7","attachment":"vfx/shouji/shouji_tx7_29","blend":"additive"}],"skins":{"default":{"hit/pojun_hit2_0":{"hit/pojun_hit2_00":{"width":900,"height":900}},"hit/pojun_hit2_00":{"hit/pojun_hit2_00":{"width":900,"height":900}},"hit/pojun_hit3_0":{"hit/pojun_hit3_00":{"width":900,"height":900},"hit/pojun_hit3_01":{"width":900,"height":900},"hit/pojun_hit3_02":{"width":900,"height":900},"hit/pojun_hit3_03":{"width":900,"height":900},"hit/pojun_hit3_04":{"width":900,"height":900},"hit/pojun_hit3_05":{"width":900,"height":900},"hit/pojun_hit3_06":{"width":900,"height":900},"hit/pojun_hit3_07":{"width":900,"height":900},"hit/pojun_hit3_08":{"width":900,"height":900},"hit/pojun_hit3_09":{"width":900,"height":900}},"hit/pojun_hit3_00":{"hit/pojun_hit3_00":{"width":900,"height":900},"hit/pojun_hit3_01":{"width":900,"height":900},"hit/pojun_hit3_02":{"width":900,"height":900},"hit/pojun_hit3_03":{"width":900,"height":900},"hit/pojun_hit3_04":{"width":900,"height":900},"hit/pojun_hit3_05":{"width":900,"height":900},"hit/pojun_hit3_06":{"width":900,"height":900},"hit/pojun_hit3_07":{"width":900,"height":900},"hit/pojun_hit3_08":{"width":900,"height":900},"hit/pojun_hit3_09":{"width":900,"height":900}},"hit/pojun_hit5_00":{"hit/pojun_hit5_00":{"width":900,"height":900}},"hit/pojun_hit6_00":{"hit/pojun_hit6_00":{"width":900,"height":900},"hit/pojun_hit6_01":{"width":900,"height":900},"hit/pojun_hit6_02":{"width":900,"height":900},"hit/pojun_hit6_03":{"width":900,"height":900},"hit/pojun_hit6_04":{"width":900,"height":900},"hit/pojun_hit6_05":{"width":900,"height":900},"hit/pojun_hit6_06":{"width":900,"height":900},"hit/pojun_hit6_07":{"width":900,"height":900},"hit/pojun_hit6_08":{"width":900,"height":900},"hit/pojun_hit6_09":{"width":900,"height":900}},"hit/pojun_hit7_00":{"hit/pojun_hit7_00":{"width":900,"height":900},"hit/pojun_hit7_01":{"width":900,"height":900},"hit/pojun_hit7_02":{"width":900,"height":900},"hit/pojun_hit7_03":{"width":900,"height":900},"hit/pojun_hit7_04":{"width":900,"height":900},"hit/pojun_hit7_05":{"width":900,"height":900},"hit/pojun_hit7_06":{"width":900,"height":900},"hit/pojun_hit7_07":{"width":900,"height":900},"hit/pojun_hit7_08":{"width":900,"height":900},"hit/pojun_hit7_09":{"width":900,"height":900}},"vfx/shouji/shouji_tx1":{"vfx/shouji/shouji_tx1":{"width":256,"height":256}},"vfx/shouji/shouji_tx8":{"vfx/shouji/shouji_tx6":{"width":900,"height":900}},"vfx/shouji/shouji_tx2_00_bl_add":{"vfx/shouji/shouji_tx2_00":{"width":900,"height":900},"vfx/shouji/shouji_tx2_01":{"width":900,"height":900},"vfx/shouji/shouji_tx2_02":{"width":900,"height":900},"vfx/shouji/shouji_tx2_03":{"width":900,"height":900},"vfx/shouji/shouji_tx2_04":{"width":900,"height":900},"vfx/shouji/shouji_tx2_05":{"width":900,"height":900},"vfx/shouji/shouji_tx2_06":{"width":900,"height":900},"vfx/shouji/shouji_tx2_07":{"width":900,"height":900},"vfx/shouji/shouji_tx2_08":{"width":900,"height":900},"vfx/shouji/shouji_tx2_09":{"width":900,"height":900},"vfx/shouji/shouji_tx2_10":{"width":900,"height":900},"vfx/shouji/shouji_tx2_11":{"width":900,"height":900},"vfx/shouji/shouji_tx2_12":{"width":900,"height":900},"vfx/shouji/shouji_tx2_13":{"width":900,"height":900},"vfx/shouji/shouji_tx2_14":{"width":900,"height":900},"vfx/shouji/shouji_tx2_15":{"width":900,"height":900},"vfx/shouji/shouji_tx2_16":{"width":900,"height":900}},"vfx/shouji/shouji_tx3_bl_add":{"vfx/shouji/shouji_tx3":{"width":207,"height":252}},"vfx/shouji/shouji_tx4_bl_add":{"vfx/shouji/shouji_tx4":{"x":112.81,"y":6.18,"width":512,"height":256}},"vfx/shouji/shouji_tx5_bl_add":{"vfx/shouji/shouji_tx4":{"x":112.81,"y":6.18,"width":512,"height":256}},"vfx/shouji/shouji_tx6_bl_add":{"vfx/shouji/shouji_tx4":{"x":112.81,"y":6.18,"width":512,"height":256}},"hit/pojun_hit4_00_bl_add":{"hit/pojun_hit4_00":{"width":900,"height":900},"hit/pojun_hit4_01":{"width":900,"height":900},"hit/pojun_hit4_02":{"width":900,"height":900},"hit/pojun_hit4_03":{"width":900,"height":900},"hit/pojun_hit4_04":{"width":900,"height":900},"hit/pojun_hit4_05":{"width":900,"height":900},"hit/pojun_hit4_06":{"width":900,"height":900},"hit/pojun_hit4_07":{"width":900,"height":900},"hit/pojun_hit4_08":{"width":900,"height":900},"hit/pojun_hit4_09":{"width":900,"height":900}},"hit/pojun_hit4_0_bl_add":{"hit/pojun_hit4_00":{"width":900,"height":900},"hit/pojun_hit4_01":{"width":900,"height":900},"hit/pojun_hit4_02":{"width":900,"height":900},"hit/pojun_hit4_03":{"width":900,"height":900},"hit/pojun_hit4_04":{"width":900,"height":900},"hit/pojun_hit4_05":{"width":900,"height":900},"hit/pojun_hit4_06":{"width":900,"height":900},"hit/pojun_hit4_07":{"width":900,"height":900},"hit/pojun_hit4_08":{"width":900,"height":900},"hit/pojun_hit4_09":{"width":900,"height":900}},"vfx/shouji/shouji_tx7_bl_add":{"vfx/shouji/shouji_tx5":{"width":493,"height":489}},"vfx/shouji/shouji_tx7_00_bl_add":{"vfx/shouji/shouji_tx7_00":{"width":900,"height":900},"vfx/shouji/shouji_tx7_01":{"width":900,"height":900},"vfx/shouji/shouji_tx7_02":{"width":900,"height":900},"vfx/shouji/shouji_tx7_03":{"width":900,"height":900},"vfx/shouji/shouji_tx7_04":{"width":900,"height":900},"vfx/shouji/shouji_tx7_05":{"width":900,"height":900},"vfx/shouji/shouji_tx7_06":{"width":900,"height":900},"vfx/shouji/shouji_tx7_07":{"width":900,"height":900},"vfx/shouji/shouji_tx7_08":{"width":900,"height":900},"vfx/shouji/shouji_tx7_09":{"width":900,"height":900},"vfx/shouji/shouji_tx7_10":{"width":900,"height":900},"vfx/shouji/shouji_tx7_11":{"width":900,"height":900},"vfx/shouji/shouji_tx7_12":{"width":900,"height":900},"vfx/shouji/shouji_tx7_13":{"width":900,"height":900},"vfx/shouji/shouji_tx7_14":{"width":900,"height":900},"vfx/shouji/shouji_tx7_15":{"width":900,"height":900},"vfx/shouji/shouji_tx7_16":{"width":900,"height":900},"vfx/shouji/shouji_tx7_17":{"width":900,"height":900},"vfx/shouji/shouji_tx7_18":{"width":900,"height":900},"vfx/shouji/shouji_tx7_19":{"width":900,"height":900},"vfx/shouji/shouji_tx7_20":{"width":900,"height":900},"vfx/shouji/shouji_tx7_21":{"width":900,"height":900},"vfx/shouji/shouji_tx7_22":{"width":900,"height":900},"vfx/shouji/shouji_tx7_23":{"width":900,"height":900},"vfx/shouji/shouji_tx7_24":{"width":900,"height":900},"vfx/shouji/shouji_tx7_25":{"width":900,"height":900},"vfx/shouji/shouji_tx7_26":{"width":900,"height":900},"vfx/shouji/shouji_tx7_27":{"width":900,"height":900},"vfx/shouji/shouji_tx7_28":{"width":900,"height":900},"vfx/shouji/shouji_tx7_29":{"width":900,"height":900}}}},"animations":{"play":{"slots":{"hit/pojun_hit2_00":{"color":[{"time":0.4333,"color":"fffffffe"},{"time":0.6667,"color":"ffffff00"}],"attachment":[{"time":0,"name":null},{"time":0.2,"name":"hit/pojun_hit2_00"},{"time":0.6667,"name":"hit/pojun_hit2_00"}]},"hit/pojun_hit2_0":{"color":[{"time":0.7333,"color":"fffffffe"},{"time":0.9667,"color":"ffffff00"}],"attachment":[{"time":0,"name":null},{"time":0.5,"name":"hit/pojun_hit2_00"},{"time":0.9667,"name":"hit/pojun_hit2_00"}]},"hit/pojun_hit3_00":{"attachment":[{"time":0,"name":null},{"time":0.1667,"name":"hit/pojun_hit3_00"},{"time":0.2,"name":"hit/pojun_hit3_01"},{"time":0.2333,"name":"hit/pojun_hit3_02"},{"time":0.2667,"name":"hit/pojun_hit3_03"},{"time":0.3,"name":"hit/pojun_hit3_04"},{"time":0.3333,"name":"hit/pojun_hit3_05"},{"time":0.3667,"name":"hit/pojun_hit3_06"},{"time":0.4,"name":"hit/pojun_hit3_07"},{"time":0.4333,"name":"hit/pojun_hit3_08"},{"time":0.4667,"name":"hit/pojun_hit3_09"},{"time":0.5,"name":null}]},"hit/pojun_hit3_0":{"attachment":[{"time":0,"name":null},{"time":0.4667,"name":"hit/pojun_hit3_00"},{"time":0.5,"name":"hit/pojun_hit3_01"},{"time":0.5333,"name":"hit/pojun_hit3_02"},{"time":0.5667,"name":"hit/pojun_hit3_03"},{"time":0.6,"name":"hit/pojun_hit3_04"},{"time":0.6333,"name":"hit/pojun_hit3_05"},{"time":0.6667,"name":"hit/pojun_hit3_06"},{"time":0.7,"name":"hit/pojun_hit3_07"},{"time":0.7333,"name":"hit/pojun_hit3_08"},{"time":0.7667,"name":"hit/pojun_hit3_09"}]},"hit/pojun_hit5_00":{"color":[{"time":0.4333,"color":"fffffffe"},{"time":0.7667,"color":"ffffff00"}],"attachment":[{"time":0,"name":null},{"time":0.4333,"name":"hit/pojun_hit5_00"},{"time":0.7667,"name":null}]},"hit/pojun_hit6_00":{"attachment":[{"time":0,"name":null},{"time":0.3667,"name":"hit/pojun_hit6_00"},{"time":0.4,"name":"hit/pojun_hit6_01"},{"time":0.4333,"name":"hit/pojun_hit6_02"},{"time":0.4667,"name":"hit/pojun_hit6_03"},{"time":0.5,"name":"hit/pojun_hit6_04"},{"time":0.5333,"name":"hit/pojun_hit6_05"},{"time":0.5667,"name":"hit/pojun_hit6_06"},{"time":0.6,"name":"hit/pojun_hit6_07"},{"time":0.6333,"name":"hit/pojun_hit6_08"},{"time":0.6667,"name":"hit/pojun_hit6_09"},{"time":0.7,"name":null}]},"hit/pojun_hit7_00":{"attachment":[{"time":0,"name":null},{"time":0.2667,"name":"hit/pojun_hit7_00"},{"time":0.3,"name":"hit/pojun_hit7_01"},{"time":0.3333,"name":"hit/pojun_hit7_02"},{"time":0.3667,"name":"hit/pojun_hit7_03"},{"time":0.4,"name":"hit/pojun_hit7_04"},{"time":0.4333,"name":"hit/pojun_hit7_05"},{"time":0.4667,"name":"hit/pojun_hit7_06"},{"time":0.5,"name":"hit/pojun_hit7_07"},{"time":0.5333,"name":"hit/pojun_hit7_08"},{"time":0.5667,"name":"hit/pojun_hit7_09"},{"time":0.6,"name":null}]},"vfx/shouji/shouji_tx1":{"color":[{"time":0.2,"color":"fffffffe"},{"time":0.7667,"color":"ffffff00"}]},"vfx/shouji/shouji_tx8":{"color":[{"time":0,"color":"ffffff00"},{"time":0.3333,"color":"fffffffe","curve":"stepped"},{"time":0.7333,"color":"fffffffe"},{"time":1.1667,"color":"ffffff00"}]},"vfx/shouji/shouji_tx2_00_bl_add":{"attachment":[{"time":0,"name":"vfx/shouji/shouji_tx2_00"},{"time":0.0333,"name":"vfx/shouji/shouji_tx2_01"},{"time":0.0667,"name":"vfx/shouji/shouji_tx2_02"},{"time":0.1,"name":"vfx/shouji/shouji_tx2_03"},{"time":0.1333,"name":"vfx/shouji/shouji_tx2_04"},{"time":0.1667,"name":"vfx/shouji/shouji_tx2_05"},{"time":0.2,"name":"vfx/shouji/shouji_tx2_06"},{"time":0.2333,"name":"vfx/shouji/shouji_tx2_07"},{"time":0.2667,"name":"vfx/shouji/shouji_tx2_08"},{"time":0.3,"name":"vfx/shouji/shouji_tx2_09"},{"time":0.3333,"name":"vfx/shouji/shouji_tx2_10"},{"time":0.3667,"name":"vfx/shouji/shouji_tx2_11"},{"time":0.4,"name":"vfx/shouji/shouji_tx2_12"},{"time":0.4333,"name":"vfx/shouji/shouji_tx2_13"},{"time":0.4667,"name":"vfx/shouji/shouji_tx2_14"},{"time":0.5,"name":"vfx/shouji/shouji_tx2_15"},{"time":0.5333,"name":"vfx/shouji/shouji_tx2_16"},{"time":0.5667,"name":null}]},"vfx/shouji/shouji_tx3_bl_add":{"color":[{"time":1,"color":"fffffffe"},{"time":1.3333,"color":"ffffff00"}]},"vfx/shouji/shouji_tx4_bl_add":{"color":[{"time":0.7333,"color":"fffffffe"},{"time":1.0667,"color":"ffffff00"}],"attachment":[{"time":0,"name":null},{"time":0.2333,"name":"vfx/shouji/shouji_tx4"}]},"vfx/shouji/shouji_tx5_bl_add":{"color":[{"time":0.0667,"color":"ffffff00"},{"time":0.1667,"color":"fffffffe"},{"time":0.6667,"color":"ffffff06"}],"attachment":[{"time":0,"name":null},{"time":0.0667,"name":"vfx/shouji/shouji_tx4"}]},"vfx/shouji/shouji_tx6_bl_add":{"color":[{"time":0.3333,"color":"ffffff00"},{"time":0.4333,"color":"fffffffe"},{"time":0.9333,"color":"ffffff06"}],"attachment":[{"time":0,"name":null},{"time":0.3333,"name":"vfx/shouji/shouji_tx4"}]},"hit/pojun_hit4_00_bl_add":{"attachment":[{"time":0.0333,"name":"hit/pojun_hit4_00"},{"time":0.0667,"name":"hit/pojun_hit4_01"},{"time":0.1,"name":"hit/pojun_hit4_02"},{"time":0.1333,"name":"hit/pojun_hit4_03"},{"time":0.1667,"name":"hit/pojun_hit4_04"},{"time":0.2,"name":"hit/pojun_hit4_05"},{"time":0.2333,"name":"hit/pojun_hit4_06"},{"time":0.2667,"name":"hit/pojun_hit4_07"},{"time":0.3,"name":"hit/pojun_hit4_08"},{"time":0.3333,"name":"hit/pojun_hit4_09"},{"time":0.3667,"name":"hit/pojun_hit4_09"},{"time":0.4,"name":null}]},"hit/pojun_hit4_0_bl_add":{"attachment":[{"time":0,"name":null},{"time":0.3333,"name":"hit/pojun_hit4_00"},{"time":0.3667,"name":"hit/pojun_hit4_01"},{"time":0.4,"name":"hit/pojun_hit4_02"},{"time":0.4333,"name":"hit/pojun_hit4_03"},{"time":0.4667,"name":"hit/pojun_hit4_04"},{"time":0.5,"name":"hit/pojun_hit4_05"},{"time":0.5333,"name":"hit/pojun_hit4_06"},{"time":0.5667,"name":"hit/pojun_hit4_07"},{"time":0.6,"name":"hit/pojun_hit4_08"},{"time":0.6333,"name":"hit/pojun_hit4_09"},{"time":0.6667,"name":"hit/pojun_hit4_09"},{"time":0.7,"name":null}]},"vfx/shouji/shouji_tx7_bl_add":{"color":[{"time":0.0667,"color":"ffffff04"},{"time":0.1333,"color":"fffffffe"},{"time":0.2333,"color":"ffffff00","curve":"stepped"},{"time":0.3,"color":"ffffff00"},{"time":0.3333,"color":"ffffffb4"},{"time":0.5,"color":"ffffff00"}],"attachment":[{"time":0,"name":null},{"time":0.0667,"name":"vfx/shouji/shouji_tx5"}]},"vfx/shouji/shouji_tx7_00_bl_add":{"attachment":[{"time":0,"name":null},{"time":0.0667,"name":"vfx/shouji/shouji_tx7_00"},{"time":0.1,"name":"vfx/shouji/shouji_tx7_01"},{"time":0.1333,"name":"vfx/shouji/shouji_tx7_02"},{"time":0.1667,"name":"vfx/shouji/shouji_tx7_03"},{"time":0.2,"name":"vfx/shouji/shouji_tx7_04"},{"time":0.2333,"name":"vfx/shouji/shouji_tx7_05"},{"time":0.2667,"name":"vfx/shouji/shouji_tx7_06"},{"time":0.3,"name":"vfx/shouji/shouji_tx7_07"},{"time":0.3333,"name":"vfx/shouji/shouji_tx7_08"},{"time":0.3667,"name":"vfx/shouji/shouji_tx7_09"},{"time":0.4,"name":"vfx/shouji/shouji_tx7_10"},{"time":0.4333,"name":"vfx/shouji/shouji_tx7_11"},{"time":0.4667,"name":"vfx/shouji/shouji_tx7_12"},{"time":0.5,"name":"vfx/shouji/shouji_tx7_13"},{"time":0.5333,"name":"vfx/shouji/shouji_tx7_14"},{"time":0.5667,"name":"vfx/shouji/shouji_tx7_15"},{"time":0.6,"name":"vfx/shouji/shouji_tx7_16"},{"time":0.6333,"name":"vfx/shouji/shouji_tx7_17"},{"time":0.6667,"name":"vfx/shouji/shouji_tx7_18"},{"time":0.7,"name":"vfx/shouji/shouji_tx7_19"},{"time":0.7333,"name":"vfx/shouji/shouji_tx7_20"},{"time":0.7667,"name":"vfx/shouji/shouji_tx7_21"},{"time":0.8,"name":"vfx/shouji/shouji_tx7_22"},{"time":0.8333,"name":"vfx/shouji/shouji_tx7_23"},{"time":0.8667,"name":"vfx/shouji/shouji_tx7_24"},{"time":0.9,"name":"vfx/shouji/shouji_tx7_25"},{"time":0.9333,"name":"vfx/shouji/shouji_tx7_26"},{"time":0.9667,"name":"vfx/shouji/shouji_tx7_27"},{"time":1,"name":"vfx/shouji/shouji_tx7_28"},{"time":1.0333,"name":"vfx/shouji/shouji_tx7_29"},{"time":1.0667,"name":null}]}},"bones":{"pojun_hit2":{"translate":[{"time":0.2,"x":0,"y":0},{"time":0.6667,"x":-14.95,"y":-18.52}]},"pojun_hit5":{"rotate":[{"time":0,"angle":-19.97}],"translate":[{"time":0,"x":19.88,"y":9.26}]},"pojun_hit6":{"rotate":[{"time":0,"angle":-21.49}],"translate":[{"time":0,"x":18.81,"y":9.34}]},"pojun_hit7":{"rotate":[{"time":0,"angle":-21.49}],"translate":[{"time":0,"x":-38.62,"y":87.63}]},"shouji_tx2":{"scale":[{"time":0,"x":1,"y":1},{"time":0.6667,"x":1.196,"y":1.196}]},"bone":{"translate":[{"time":0.2333,"x":-298.93,"y":0},{"time":0.5667,"x":198.02,"y":0},{"time":1.0667,"x":244.66,"y":0}],"scale":[{"time":0.2333,"x":2,"y":2},{"time":0.4,"x":1.43,"y":0.3},{"time":0.5667,"x":1.43,"y":0.1},{"time":0.9,"x":1.43,"y":0.02}]},"shouji_tx4_1":{"rotate":[{"time":0,"angle":-50}],"translate":[{"time":0,"x":-66.52,"y":82.74}],"scale":[{"time":0,"x":0.6,"y":1}]},"bone2":{"translate":[{"time":0.0667,"x":0,"y":-81.2},{"time":0.1667,"x":0,"y":89.9},{"time":0.6667,"x":0,"y":129.05}],"scale":[{"time":0.0667,"x":1.68,"y":1.46,"curve":"stepped"},{"time":0.1667,"x":1.68,"y":1.46},{"time":0.3,"x":1.68,"y":0.14},{"time":0.5333,"x":1.68,"y":0.02}]},"shouji_tx4_2":{"rotate":[{"time":0,"angle":-33}],"translate":[{"time":0,"x":-119.78,"y":-196.75}]},"hit":{"rotate":[{"time":0,"angle":4.54}],"translate":[{"time":0,"x":1.24,"y":0}],"scale":[{"time":0,"x":0.86,"y":0.86},{"time":0.3333,"x":1,"y":1}]},"bone3":{"translate":[{"time":0.3333,"x":0,"y":-81.2},{"time":0.4333,"x":0,"y":89.9},{"time":0.9333,"x":0,"y":129.05}],"scale":[{"time":0.3333,"x":1.68,"y":1.46,"curve":"stepped"},{"time":0.4333,"x":1.68,"y":1.46},{"time":0.5667,"x":1.68,"y":0.14},{"time":0.8,"x":1.68,"y":0.02}]},"shouji_tx4_3":{"rotate":[{"time":0,"angle":102}],"translate":[{"time":0,"x":287.8,"y":44.3}]},"shouji_tx4":{"scale":[{"time":0,"x":0.699,"y":0.699}]},"pojun_hit8":{"translate":[{"time":0.5,"x":0,"y":0},{"time":0.9667,"x":-14.95,"y":-18.52}],"scale":[{"time":0,"x":0.969,"y":0.969}]},"pojun_hit9":{"scale":[{"time":0,"x":0.969,"y":0.969}]},"pojun_hit10":{"scale":[{"time":0,"x":0.969,"y":0.969}]},"hit2":{"rotate":[{"time":0,"angle":140.85}],"translate":[{"time":0,"x":-11.46,"y":-17.57}],"scale":[{"time":0,"x":0.759,"y":0.759},{"time":0.6667,"x":0.85,"y":0.85}]}}}}}